LICENSE
README.rst
setup.cfg
setup.py
freelancehunt/__init__.py
freelancehunt/__main__.py
freelancehunt/client.py
freelancehunt/core.py
freelancehunt/version.py
freelancehunt/models/bid.py
freelancehunt/models/budget.py
freelancehunt/models/city.py
freelancehunt/models/contest.py
freelancehunt/models/country.py
freelancehunt/models/feed.py
freelancehunt/models/project.py
freelancehunt/models/review.py
freelancehunt/models/skill.py
freelancehunt/models/thread.py
freelancehunt/models/user.py
freelancehunt/packages/bids.py
freelancehunt/packages/cities.py
freelancehunt/packages/contests.py
freelancehunt/packages/countries.py
freelancehunt/packages/feed.py
freelancehunt/packages/profiles.py
freelancehunt/packages/projects.py
freelancehunt/packages/reviews.py
freelancehunt/packages/skills.py
freelancehunt/packages/threads.py
freelancehunt/utils/errors.py
freelancehunt/utils/requester.py
freelancehunt_api.egg-info/PKG-INFO
freelancehunt_api.egg-info/SOURCES.txt
freelancehunt_api.egg-info/dependency_links.txt
freelancehunt_api.egg-info/requires.txt
freelancehunt_api.egg-info/top_level.txt