Metadata-Version: 2.1
Name: freelancehunt-api
Version: 0.1.3
Summary: FreelanceHunt API Python library
Home-page: https://github.com/dmytrohoi/freelancehunt-api
Author: Dmytro Hoi
Author-email: code@dmytrohoi.com
License: MIT License
Keywords: python freelance api wrapper
Platform: UNKNOWN
Classifier: Development Status :: 3 - Alpha
Classifier: Intended Audience :: Developers
Classifier: License :: OSI Approved :: MIT License
Classifier: Operating System :: OS Independent
Classifier: Topic :: Software Development :: Libraries :: Python Modules
Classifier: Topic :: Internet
Classifier: Programming Language :: Python
Classifier: Programming Language :: Python :: 3
Classifier: Programming Language :: Python :: 3.6
Classifier: Programming Language :: Python :: 3.7
Classifier: Programming Language :: Python :: 3.8
